fir.v
module fir_filter (
    input clk,           // Clock signal
    input rst_n,         // Active low reset
    input signed [15:0] x_in,  // Input data (16-bit signed)
    output reg signed [15:0] y_out // Filtered output data (16-bit signed)
);

    // Define the filter coefficients (example with 4 taps)
    reg signed [15:0] coeffs [0:3]; // 4 taps
    reg signed [15:0] delay_line [0:3]; // Delay line to store previous inputs
    
    integer i;

    // Initializing filter coefficients
    initial begin
        coeffs[0] = 16'h0004;  // Coefficients for FIR filter
        coeffs[1] = 16'h0008;
        coeffs[2] = 16'h0008;
        coeffs[3] = 16'h0004;
    end

    // Process input on every clock edge
    always @(posedge clk or negedge rst_n) begin
        if (!rst_n) begin
            // Reset delay line and output
            for (i = 0; i < 4; i = i + 1) begin
                delay_line[i] <= 16'h0000;
            end
            y_out <= 16'h0000;
        end else begin
            // Shift the delay line
            for (i = 3; i > 0; i = i - 1) begin
                delay_line[i] <= delay_line[i-1];
            end
            // Load new input into delay line
            delay_line[0] <= x_in;

            // FIR filter computation
            y_out <= (delay_line[0] * coeffs[0]) + 
                     (delay_line[1] * coeffs[1]) + 
                     (delay_line[2] * coeffs[2]) + 
                     (delay_line[3] * coeffs[3]);
        end
    end
endmodule

fir_tb.v
module tb_fir_filter;

    reg clk;
    reg rst_n;
    reg signed [15:0] x_in;
    wire signed [15:0] y_out;

    // Instantiate the FIR filter
    fir_filter uut (
        .clk(clk),
        .rst_n(rst_n),
        .x_in(x_in),
        .y_out(y_out)
    );

    // Clock generation
    always begin
        #5 clk = ~clk;  // 10ns period
    end

    // Testbench logic
    initial begin
        // Initialize signals
        clk = 0;
        rst_n = 0;
        x_in = 16'h0000;

        // Apply reset
        #10 rst_n = 1;

        // Apply input stimulus
        #10 x_in = 16'h0001;  // Sample input 1
        #10 x_in = 16'h0002;  // Sample input 2
        #10 x_in = 16'h0003;  // Sample input 3
        #10 x_in = 16'h0004;  // Sample input 4
        #10 x_in = 16'h0005;  // Sample input 5

        // Finish simulation
        #50 $finish;
    end

    // Monitor output
    initial begin
        $monitor("Time: %0t, Input: %h, Output: %h", $time, x_in, y_out);
    end

    initial begin
        $dumpfile("dump.vcd");
        $dumpvars(0);
    end

endmodule

dump.vcd
$date
	Mon Dec 30 11:21:44 2024
$end
$version
	Icarus Verilog
$end
$timescale
	1s
$end
$scope module tb_fir_filter $end
$var wire 16 ! y_out [15:0] $end
$var reg 1 " clk $end
$var reg 1 # rst_n $end
$var reg 16 $ x_in [15:0] $end
$scope module uut $end
$var wire 1 " clk $end
$var wire 1 # rst_n $end
$var wire 16 % x_in [15:0] $end
$var reg 16 & y_out [15:0] $end
$var integer 32 ' i [31:0] $end
$upscope $end
$upscope $end
$enddefinitions $end
$comment Show the parameter values. $end
$dumpall
$end
#0
$dumpvars
b100 '
b0 &
b0 %
b0 $
0#
0"
b0 !
$end
#5
b100 '
1"
#10
0"
1#
#15
b0 '
1"
#20
0"
b1 $
b1 %
#25
b0 '
1"
#30
0"
b10 $
b10 %
#35
b100 !
b100 &
b0 '
1"
#40
0"
b11 $
b11 %
#45
b10000 !
b10000 &
b0 '
1"
#50
0"
b100 $
b100 %
#55
b100100 !
b100100 &
b0 '
1"
#60
0"
b101 $
b101 %
#65
b111100 !
b111100 &
b0 '
1"
#70
0"
#75
b1010100 !
b1010100 &
b0 '
1"
#80
0"
#85
b1101000 !
b1101000 &
b0 '
1"
#90
0"
#95
b1110100 !
b1110100 &
b0 '
1"
#100
0"
#105
b1111000 !
b1111000 &
b0 '
1"
